sysappend/__init__.py
sysappend/py.typed
sysappend/version.py
sysappend-1.6.2.dist-info/LICENSE
sysappend-1.6.2.dist-info/METADATA
sysappend-1.6.2.dist-info/WHEEL
sysappend-1.6.2.dist-info/top_level.txt
sysappend-1.6.2.dist-info/RECORD
